.gitignore
CHANGES.rst
MANIFEST.in
README.rst
setup.py
collective/__init__.py
collective.csv2dict.egg-info/PKG-INFO
collective.csv2dict.egg-info/SOURCES.txt
collective.csv2dict.egg-info/dependency_links.txt
collective.csv2dict.egg-info/namespace_packages.txt
collective.csv2dict.egg-info/not-zip-safe
collective.csv2dict.egg-info/requires.txt
collective.csv2dict.egg-info/top_level.txt
collective/csv2dict/__init__.py
collective/csv2dict/example.csv
collective/csv2dict/example.py
collective/csv2dict/readers.py
collective/csv2dict/utils.py
docs/LICENSE.GPL
docs/LICENSE.txt