Metadata-Version: 1.1
Name: collective.csv2dict
Version: 1.1
Summary: Turn a csv into a dictionary with a predefined schema.
Home-page: https://github.com/collective/collective.csv2dict
Author: Maurits van Rees
Author-email: m.van.rees@zestsoftware.nl
License: GPL
Platform: UNKNOWN
Classifier: Programming Language :: Python
